[
    {
        "title": "Shunya se Superpower:  Decoding Quantum Supremacy",
        "date": "30 June, 2025",
        "post_path": "posts/2025-06-30-shunya-se-superpower-decoding-quantum-supremacy/post.md",
        "slug": "shunya-se-superpower-decoding-quantum-supremacy",
        "read_time": 3,
        "excerpt": "Shunya se Superpower: Decoding Quantum Supremacy...",
        "category": "Quantum"
    },
    {
        "title": "5G से परे: क्या 6G लाएगा  'डिजिटल अवतार' की क्रांति?",
        "date": "30 June, 2025",
        "post_path": "posts/2025-06-30-5g-स-पर-कय-6g-लएग-डजटल-अवतर-क-करत/post.md",
        "slug": "5g-स-पर-कय-6g-लएग-डजटल-अवतर-क-करत",
        "read_time": 4,
        "excerpt": "6G: क्या डिजिटल अवतारों का युग आने वाला है?...",
        "category": "The"
    },
    {
        "title": "भविष्य की तकनीक: आर्टिफिशियल इंटेलिजेंस और इसके अनुप्रयोग",
        "date": "30 June, 2025",
        "post_path": "posts/2025-06-30-भवषय-क-तकनक-आरटफशयल-इटलजस-और-इसक-अनपरयग/post.md",
        "slug": "भवषय-क-तकनक-आरटफशयल-इटलजस-और-इसक-अनपरयग",
        "read_time": 3,
        "excerpt": "भविष्य का जादू: आर्टिफिशियल इंटेलिजेंस और उसके अद्भुत अनुप्रयोग!..."
    },
    {
        "title": "भारत में कृत्रिम बुद्धिमत्ता का भविष्य (Bharat mein Kritim Buddhimataa ka Bhavishya)",
        "date": "30 June, 2025",
        "post_path": "posts/2025-06-30-भ-रत-म-क-त-र-म-ब-द-ध-मत-त-क-भव-ष-य-bharat-mein-kritim-buddhimataa-ka-bhavishya/post.md",
        "slug": "भ-रत-म-क-त-र-म-ब-द-ध-मत-त-क-भव-ष-य-bharat-mein-kritim-buddhimataa-ka-bhavishya"
    }
]